KeGen/__init__.py
kegen-0.0.2.dist-info/METADATA
kegen-0.0.2.dist-info/WHEEL
kegen-0.0.2.dist-info/licenses/LICENSE
kegen-0.0.2.dist-info/RECORD
