Metadata-Version: 2.4
Name: KeGen
Version: 0.0.2
Summary: A simple key generator
Project-URL: Homepage, https://github.com/M-suri/M.S.M-libraries/tree/main/lib/KeGen
Project-URL: Issues, https://github.com/M-suri/M.S.M-libraries/tree/main/lib/KeGen
Author-email: Mario Sperandio Marato <s.mario12112009@gmail.com>
License-File: LICENSE
Classifier: License :: OSI Approved :: GNU General Public License v3 (GPLv3)
Classifier: Operating System :: OS Independent
Classifier: Programming Language :: Python :: 3
Requires-Python: >=3.0
